Impuestos_Internos_Helper-1.0.1.data/data/data/impuestos_internos.py
Impuestos_Internos_Helper-1.0.1.dist-info/DESCRIPTION.rst
Impuestos_Internos_Helper-1.0.1.dist-info/METADATA
Impuestos_Internos_Helper-1.0.1.dist-info/RECORD
Impuestos_Internos_Helper-1.0.1.dist-info/WHEEL
Impuestos_Internos_Helper-1.0.1.dist-info/metadata.json
Impuestos_Internos_Helper-1.0.1.dist-info/top_level.txt
data/__init__.py
data/data/__init__.py
data/lib/__init__.py
data/lib/impuestos_internos.py
data/tests/__init__.py
data/tests/reader.py
