Metadata-Version: 2.0
Name: Impuestos-Internos-Helper
Version: 1.0.1
Summary: Generador de codigo de control V7 para Impuestos Internos.
Home-page: https://github.com/drkpkg/codigo_control
Author: drkpkg
Author-email: daniel.uremix@gmail.com
License: UNKNOWN
Keywords: impuestos bolivia
Platform: UNKNOWN
Classifier: Development Status :: 5 - Production/Stable
Classifier: Intended Audience :: Developers
Classifier: Topic :: Software Development :: Build Tools
Classifier: License :: OSI Approved :: MIT License
Classifier: Programming Language :: Python :: 2.7
Classifier: Programming Language :: Python :: 3
Classifier: Programming Language :: Python :: 3.4
Classifier: Programming Language :: Python :: 3.5
Classifier: Programming Language :: Python :: 3.6
Requires-Dist: qrcode
Provides-Extra: dev
Requires-Dist: check-manifest; extra == 'dev'
Provides-Extra: test
Requires-Dist: coverage; extra == 'test'
